pandas_etl/__init__.py
pandas_etl/__main__.py
pandas_etl/etl.py
pandas_etl-2022.8.17.1.dist-info/LICENSE
pandas_etl-2022.8.17.1.dist-info/METADATA
pandas_etl-2022.8.17.1.dist-info/WHEEL
pandas_etl-2022.8.17.1.dist-info/top_level.txt
pandas_etl-2022.8.17.1.dist-info/RECORD
