Metadata-Version: 2.1
Name: pandas-etl
Version: 2022.8.17.1
Summary: A utility for running YAML config as Pandas based ETL code
Author-email: "Righteous AI Inc." <admin@righteous.ai>
License: MIT License        
Keywords: pandas-etl,pandas_etl,call,yaml
Classifier: Intended Audience :: Developers
Classifier: License :: OSI Approved :: MIT License
Classifier: Operating System :: OS Independent
Classifier: Programming Language :: Python :: 3
Classifier: Programming Language :: Python :: 3.8
Classifier: Programming Language :: Python :: 3.9
Classifier: Programming Language :: Python :: 3.10
Classifier: Programming Language :: Python :: 3 :: Only
Requires-Python: >=3.8
License-File: LICENSE
Requires-Dist: colorama (>=0.4.4)
Requires-Dist: tqdm (>=4.64.0)
Requires-Dist: sqlalchemy (>=1.4.39)
